dtest/__init__.py
dtest/dtest.py
dtest/interfaces/__init__.py
dtest/interfaces/handler.py
dtest/publishers/__init__.py
dtest/publishers/restkvhandler.py
dtest/publishers/rmqhandler.py
dtest/schema/__init__.py
dtest/schema/results_schema.py
dtest/vaults/__init__.py
dtest/vaults/secretsmanager.py
tests/__init__.py
tests/test_dtest.py
tests/test_local.py
dtest_framework-0.1.23.dist-info/LICENSE
dtest_framework-0.1.23.dist-info/METADATA
dtest_framework-0.1.23.dist-info/WHEEL
dtest_framework-0.1.23.dist-info/top_level.txt
dtest_framework-0.1.23.dist-info/RECORD
