Metadata-Version: 2.1
Name: dtest-framework
Version: 0.1.23
Summary: A library to facilitate the testing of data inside data pipelines. Results are pushed to a messaging queue of some sort for consumption by applications, persistence, etc.
Home-page: https://github.com/sjensen85/dtest
Author: Seth Jensen
Author-email: sjensen85@gmail.com
License: MIT
Platform: UNKNOWN
Requires-Dist: six
Requires-Dist: pika (==1.0.0)
Requires-Dist: pyhamcrest
Requires-Dist: requests
Requires-Dist: boto3
